tests/__init__.py
tk_cyberpunk_theme/__init__.py
tk_cyberpunk_theme/__main__.py
tk_cyberpunk_theme/constant.py
tk_cyberpunk_theme/main.py
tk_cyberpunk_theme/version.py
tk_cyberpunk_theme/demo/__init__.py
tk_cyberpunk_theme/demo/demo_view.py
tk_cyberpunk_theme/native_widget/__init__.py
tk_cyberpunk_theme/native_widget/button.py
tk_cyberpunk_theme/native_widget/canvas.py
tk_cyberpunk_theme/native_widget/checkbutton.py
tk_cyberpunk_theme/native_widget/entry.py
tk_cyberpunk_theme/native_widget/frame.py
tk_cyberpunk_theme/native_widget/label.py
tk_cyberpunk_theme/native_widget/label_frame.py
tk_cyberpunk_theme/native_widget/listbox.py
tk_cyberpunk_theme/native_widget/menu.py
tk_cyberpunk_theme/native_widget/menubutton.py
tk_cyberpunk_theme/native_widget/option_menu.py
tk_cyberpunk_theme/native_widget/paned_window.py
tk_cyberpunk_theme/native_widget/radiobutton.py
tk_cyberpunk_theme/native_widget/scale.py
tk_cyberpunk_theme/native_widget/scrollbar.py
tk_cyberpunk_theme/native_widget/spinbox.py
tk_cyberpunk_theme/native_widget/text.py
tk_cyberpunk_theme/native_widget/toplevel.py
tk_cyberpunk_theme/pyrustic_widget/__init__.py
tk_cyberpunk_theme/pyrustic_widget/choice.py
tk_cyberpunk_theme/pyrustic_widget/confirm.py
tk_cyberpunk_theme/pyrustic_widget/pathentry.py
tk_cyberpunk_theme/pyrustic_widget/scrollbox.py
tk_cyberpunk_theme/pyrustic_widget/table.py
tk_cyberpunk_theme/pyrustic_widget/toast.py
tk_cyberpunk_theme/pyrustic_widget/tree.py
tk_cyberpunk_theme-0.0.5.dist-info/LICENSE
tk_cyberpunk_theme-0.0.5.dist-info/METADATA
tk_cyberpunk_theme-0.0.5.dist-info/WHEEL
tk_cyberpunk_theme-0.0.5.dist-info/entry_points.txt
tk_cyberpunk_theme-0.0.5.dist-info/top_level.txt
tk_cyberpunk_theme-0.0.5.dist-info/RECORD
