Metadata-Version: 2.1
Name: tk-cyberpunk-theme
Version: 0.0.5
Summary: The cyberpunk default theme for Pyrustic Framework
Home-page: https://github.com/pyrustic/tk-cyberpunk-theme
Author: Pyrustic Evangelist
Author-email: pyrustic@protonmail.com
Maintainer: Pyrustic Evangelist
Maintainer-email: pyrustic@protonmail.com
License: MIT
Keywords: theme,cyberpunk,dark-theme,desktop-application,tkinter,graphical,dark-theme
Platform: UNKNOWN
Classifier: Programming Language :: Python :: 3
Classifier: License :: OSI Approved :: MIT License
Classifier: Operating System :: OS Independent
Requires-Python: >=3.5
Requires-Dist: pyrustic
